{
  "Bounty": [
    "Bull Pen",
    "Burning Sands",
    "Cobweb",
    "Color Me Intrigued",
    "Crossroads",
    "Crowd Strike",
    "Cube Force",
    "Deeper Danger",
    "Dont Turn Around",
    "Electric Zone",
    "Excel",
    "Flank Attack",
    "Flanking Maneuver",
    "Heat Wave",
    "Infinite Doom",
    "Iris Intervention",
    "Iron Standoff",
    "Land Ahoy",
    "Nowhere To Hide",
    "Open Plaza",
    "Overgrown Canyon",
    "Slayers Paradise",
    "Starrburst",
    "Stone Fort",
    "Storm Attack",
    "Sunstroke",
    "The Great Open"
  ],
  "Solo Showdown": [
    "Art Team Hangout",
    "Boxed In",
    "Canyon Rivers",
    "Circular Canyon",
    "Clash Colosseum",
    "Core Crumble",
    "Core Of Orbit",
    "Critical Crossing",
    "Descending Dimensions",
    "Desert Tendrils",
    "Deserted Vertex",
    "Dried Up River",
    "Eggshell",
    "Fiftyfive",
    "Final Four",
    "Flying Fantasies",
    "Forsaken Falls",
    "Ghost Point",
    "Grassy Gorge",
    "Hard Limits",
    "Ignition",
    "Kroket",
    "Leaping Frogs",
    "Lush Poles",
    "Marksmans Paradise",
    "Mystic Touch",
    "Mystical Thirty Three",
    "Nruhc Nrevac",
    "Outrageous Outback",
    "Point Of View",
    "Risky Cliffs",
    "Riverside Ring",
    "Rocky Blocks",
    "Scorched Stone",
    "Shadow Spirits",
    "Stocky Stockades",
    "Sunset Vista",
    "Superstar",
    "The Galaxy",
    "The Mortuary",
    "Thousand Lakes",
    "Trainhaven",
    "Trap Map",
    "Treasure Hunt",
    "Vicious Vortex",
    "Victor Valley",
    "Will Of The Wisp",
    "Zoomed Out"
  ],
  "Big Game": [
    "Chew Out",
    "Hunting Party",
    "Lit Match",
    "Open Season",
    "Table Flip",
    "Team Day"
  ],
  "Heist": [
    "Bandit Cove",
    "Bandit Hook",
    "Beachcombers",
    "Cant Touch This",
    "Center Control",
    "Central Traffic",
    "Cover Crowd",
    "Crossroads",
    "Diagonal Alley",
    "Diamond Dome",
    "Double Locking",
    "Eating Good",
    "Electric Storm",
    "Fancy Fencing",
    "Figure 8",
    "Forks Out",
    "G.g. Mortuary",
    "Ghoulish Lagoon",
    "Offset Heist",
    "Rattlesnake Ravine",
    "River Banks",
    "Riverbed",
    "Rolling Rumble",
    "Secret Or Mystery",
    "Side Story",
    "Snaked Assault",
    "Split Second",
    "Spring Onions",
    "Sultans Of Swing",
    "The Great Lake",
    "Tornado Ring",
    "Traffic Jam",
    "Treefecta",
    "Turnaround"
  ],
  "Robo Rumble": [
    "Full On",
    "Keep Safe",
    "Steel Junction",
    "Vault Defenders"
  ],
  "Duo Showdown": [
    "Boxed In",
    "Brawler Speedway",
    "Canyon Rivers",
    "Circular Canyon",
    "Clash Colosseum",
    "Core Crumble",
    "Core Of Orbit",
    "Critical Crossing",
    "Descending Dimensions",
    "Desert Tendrils",
    "Deserted Vertex",
    "Dried Up River",
    "Eggshell",
    "Fiftyfive",
    "Final Four",
    "Flying Fantasies",
    "Forsaken Falls",
    "Ghost Point",
    "Grassy Gorge",
    "Hard Limits",
    "Ignition",
    "Jump Park",
    "Kroket",
    "Leaping Frogs",
    "Lush Poles",
    "Marksmans Paradise",
    "Mystic Touch",
    "Mystical Thirty Three",
    "Nruhc Nrevac",
    "Outrageous Outback",
    "Point Of View",
    "Risky Cliffs",
    "Riverside Ring",
    "Rocky Blocks",
    "Scorched Stone",
    "Shadow Spirits",
    "Stocky Stockades",
    "Sunset Vista",
    "Superstar",
    "Teleport Tag",
    "The Galaxy",
    "The Mortuary",
    "Thousand Lakes",
    "Trap Map",
    "Treasure Hunt",
    "Vicious Vortex",
    "Victor Valley",
    "Will Of The Wisp",
    "Zoomed Out"
  ],
  "Brawl Ball": [
    "Back Pocket",
    "Bank Shot",
    "Barrel Vault",
    "Binary Coding",
    "Boxing Day",
    "Center Field",
    "Circular Motion",
    "Coarse Course",
    "Crossing",
    "Curveball",
    "Deadly Deflections",
    "Double Jeopardy",
    "Encirclement",
    "Extra Bouncy",
    "Fast Fork",
    "Firm Grip",
    "Full Tilt",
    "Galaxy Arena",
    "Goalies",
    "Goalkeepers Dream",
    "Hairdryer Treatment",
    "Happy Feet",
    "High Score",
    "Iron Bars",
    "Iron Corridor",
    "Make It Bounce",
    "Off The Line",
    "Offside Trap",
    "Penalty Kick",
    "Ping Pong",
    "Playbox",
    "Post Haste",
    "Power Shot",
    "Puddle Splash",
    "Razzle Dazzle",
    "Retina",
    "Rush",
    "Second Try",
    "Shoulder Bash",
    "Side Jump",
    "Side Strike",
    "Slalom Slam",
    "Spider Crawler",
    "Square Off",
    "Sticky Notes",
    "Strange",
    "Substitute",
    "Trickey",
    "Turtle Shell",
    "Warped Beach",
    "Wavedash",
    "Weak Foot",
    "Well Cut",
    "Winter Party"
  ],
  "Boss Fight": [
    "Danger Zone",
    "Machine Zone",
    "Metal Scrap",
    "Rope-A-Dope",
    "Rumble In The Jungle"
  ],
  "Spirit Wars": [
    "Abyssal Assault",
    "Bot Riot",
    "Bric-A-Brac",
    "Celestial Crusade",
    "Crated Factory",
    "Divine Descent",
    "Factory Rush",
    "Fenced In",
    "Final Frontier",
    "Junk Park",
    "Mecha Match",
    "Olive Branch",
    "Power Washer",
    "Radiant Rampage",
    "Robo Ring",
    "Rust Belt",
    "Straight Shot",
    "Underworld Uprising"
  ],
  "Takedown": [
    "Alligator Alley",
    "Boss Drop",
    "Bulk Up",
    "Clockwork",
    "Cuckoo Coup",
    "Fractions",
    "Frenemies",
    "Funky Punk",
    "Maze Mayhem",
    "Peak Oil",
    "Poison Fields",
    "Ring Of Death",
    "Roundabout",
    "Scrap Metal",
    "Tight Stuff"
  ],
  "Lone Star": [
    "Cauliflower",
    "Crossroads",
    "Not So Safe",
    "Shore Shot",
    "Spinning Solo",
    "Stolen Valor"
  ],
  "Present Plunder": [
    "Case Of The Mondays",
    "Daylight Robbery",
    "Easy Money",
    "Maze Creep",
    "Million Dollars",
    "Oceans Six",
    "Paper Jam",
    "Roped In",
    "Side Door",
    "Sideswipe",
    "Smugglers",
    "Stolen Valor",
    "Straight Up Racket",
    "Thin Walls",
    "Trophy Trespass",
    "Twisted Plan",
    "Walk In Walk Out",
    "Zip Line"
  ],
  "Hot Zone": [
    "Breakout Brawl",
    "Checkered",
    "Controller Chaos",
    "Conveyor Clash",
    "Danger Zone",
    "Double-Sided",
    "From Dusk Till Dawn",
    "High Score",
    "Imbalance",
    "Iron Cover",
    "Local Businesses",
    "Magnetic Field",
    "Misty Meadows",
    "Night At The Museum",
    "Noisy Neighbors",
    "On The Train",
    "Over The Top",
    "Perimeter",
    "Quarter Pounder",
    "Quick Travel",
    "Reflections",
    "Rush",
    "Rush Hour",
    "Sizzling Surprise",
    "Split",
    "Street Brawler 2",
    "Temple Of Boom",
    "The Great Divide",
    "Trident",
    "Triumvirate",
    "Watch Out",
    "Watersport"
  ],
  "Super City Rampage": [
    "Super City"
  ],
  "Knockout": [
    "Belles Rock",
    "Between The Rivers",
    "Crimewater",
    "Deep Forest",
    "Double Bluff",
    "Dragon Jaws",
    "Ends Meet",
    "Flowing Springs",
    "Gratitude",
    "H For...",
    "Konnakol",
    "Luis Revenge",
    "Middle Ground",
    "Mossy Crossing",
    "Opening Move",
    "Overgrown Ruins",
    "Riverside",
    "Snake Out",
    "Splash Out",
    "Split Difference",
    "Step By Step",
    "Streets With No Name",
    "Sunset Spar",
    "Temple Of Vroom",
    "Tiny Islands",
    "Twilight Passage",
    "Two Rivers",
    "Waters Of Doom",
    "X Marks The Spot",
    "Zip Zap"
  ],
  "Carry The Gift": [
    "Cornered",
    "Elevator Pitch",
    "Hot Pursuit",
    "Medal Madness",
    "Prized Possession"
  ],
  "Volley Brawl": [
    "Floater",
    "Isolation Play",
    "Jungle Ball",
    "Pancake",
    "Power Alley",
    "Quick Attack",
    "Smash Land",
    "Strong Side",
    "Tiger Leap",
    "Victory Road"
  ],
  "Duels": [
    "Battered Battlefield",
    "Black River",
    "Breaks",
    "Burning Flares",
    "Cheeky Chokepoint",
    "Danger Chamber",
    "Death Loop",
    "Devils Pass",
    "Duelists Destiny",
    "Eyes On The Ground",
    "Four Lakes",
    "Gladiators",
    "Grim Island",
    "Hamiltons End",
    "Hotheaded",
    "Hurricane",
    "Iron Core",
    "Line Of Defense",
    "Mantis Claw",
    "Meadow Of The Crane",
    "Mogura Tataki",
    "Ninja Checkmate",
    "Petticoat Duel",
    "Pillars Of Doom",
    "Rigid Ravines",
    "Swallow Cut",
    "Swimming Skills",
    "Tangled Shrubs",
    "Tiger Trap",
    "Too Cool For Summer",
    "Warriors Way",
    "Zen Garden"
  ],
  "Wipeout": [
    "Camping Grounds",
    "Coconut Cove",
    "Covered Garden",
    "Friendly Fire Off",
    "Give And Take",
    "Infinite Doom",
    "Quad Damage",
    "Slayers Paradise",
    "Spice Production",
    "The Great Open",
    "Translocator Exchange",
    "Wicked Twig"
  ],
  "Payload": [
    "Air Waybill",
    "Backhaul",
    "Backhaul Updated",
    "Blimey",
    "Concealed Damage",
    "Cubic Capacity",
    "Davy Jones Locker",
    "Drawback",
    "Force Majeure",
    "Highly Trafficated",
    "Iron Center",
    "Lakeside Lappin",
    "Midlands",
    "Shiver Me Timbers",
    "Special Delivery",
    "Transfer Of Troubles",
    "Walk The Plank"
  ],
  "Bot Drop": [
    "A Loud Place",
    "Bots Attack",
    "Bullseye",
    "Corridors",
    "Departure",
    "Devolution",
    "Divided",
    "Forts",
    "Killzone",
    "Peekaboo",
    "Quadrants",
    "Riverside",
    "The Bot",
    "Val Verde"
  ],
  "Hunters": [
    "Deliverance",
    "Hunting Season",
    "Omega",
    "Quick And Restless",
    "The Prey",
    "Trials And Tribulations",
    "True Trail"
  ],
  "Last Stand": [
    "Dark Destiny",
    "Fried Circuits",
    "Punishment Day",
    "Rise Of The Robots",
    "Salvation",
    "The Eliminator"
  ],
  "Basket Brawl": [
    "Pick And Roll"
  ],
  "Brawl Ball 5v5": [
    "Great Waves"
  ],
  "Gem Grab 5v5": [
    "Snowflakes"
  ],
  "Trophy Escape": [
    "Bounce Bazaar",
    "Breakwater Port",
    "Circling Sands",
    "Hardihood Hideaway"
  ],
  "Godzilla City Smash": [
    "Capital Chaos",
    "Downtown Destruction"
  ],
  "Paint Brawl": [
    "Chromatic Cress",
    "Dye Direct",
    "Greasepaint Grass",
    "Rusty Rebound",
    "Spots Of Yore",
    "Spring Back Alley",
    "Tint Terrace",
    "Touch Up Tavern"
  ],
  "Soul Collector": [
    "Afterpiece Arena",
    "Broiler Room",
    "Foursquare Fortress",
    "Paperback Pond"
  ],
  "Drum Roll": [
    "Scorched Stone"
  ],
  "Trio Showdown": [
    "Bullseye",
    "Burger Bay",
    "Core Of Orbit",
    "Flying Fantasies",
    "Kroket",
    "Mystical Thirty Three",
    "Ring O Brawlin",
    "Splashing Rivers",
    "Squad Out",
    "Starr Fish",
    "Thousand Jellies"
  ],
  "Cleaning Duty": [
    "Dumpster Drive",
    "Garbage Yard",
    "Litterbug Lane",
    "Rubbish Rampage",
    "Trash Bash",
    "Waste Haven"
  ],
  "Knockout Limbo": [
    "Ends Meet"
  ],
  "Special Delivery": [
    "Corridor Creeper",
    "Dough Or Die",
    "Right On Time",
    "Triple Cheese",
    "We Messed Up"
  ],
  "Gem Grab 2v2": [
    "Buddy Brawl",
    "Cooperative Chaos",
    "Duo Dash",
    "Pair Plaza",
    "Partner Panic",
    "Tango"
  ],
  "Brawl Ball 2v2": [
    "Ball Stars",
    "Double Dribble",
    "Field Frenzy",
    "Lines Of Play",
    "Penny Drop",
    "Pitch Perfect"
  ],
  "Hot Zone 2v2": [
    "Double Play Palace",
    "Joystick Jungle",
    "Mirror Point",
    "Protected Pools"
  ],
  "Knockout 2v2": [
    "Blocky Blockade",
    "Grassy Grave",
    "Lane Of Duty",
    "Ravens Pass"
  ],
  "Basket Brawl 2v2": [
    "Buzzer Beater",
    "Dorky Dunkin",
    "Off The Charts"
  ],
  "Special Delivery 2v2": [
    "Checkpoint Chase",
    "We Messed Up"
  ],
  "Brawl Hockey 2v2": [
    "Air Sports Arena",
    "Puck Man",
    "Puck Palace",
    "Slapshot Stadium"
  ],
  "Token Run": [
    "1-2-3 Play",
    "Crazy For Credits",
    "Insert Victory",
    "Invaded Space",
    "Prize Pushing",
    "Reverse Crossing",
    "Skipyard",
    "Wild Greens"
  ],
  "Treasure Hunt": [
    "Ancient Treasure",
    "Can You Dig It",
    "Excellent Excavations",
    "Middle Management",
    "Side Quests",
    "Train Erasure",
    "Treasure Marks The Spot"
  ],
  "Samurai Smash": [
    "Battlebento Basin",
    "Dragonroll Reef",
    "Fishblade Village",
    "Maki Market",
    "Mount Sushimura",
    "Sashimi Shores",
    "Steamrise Island",
    "Tempura Valley",
    "Wasabi Fortress"
  ],
  "Hawkins Hunt": [
    "Boss Bruce Nita",
    "Boss Crow",
    "Boss Dragon Griff",
    "Boss Dragon Maisie",
    "Boss Dragrom",
    "Carreta Spike",
    "Demogorgon",
    "Ghost Diver Rico",
    "Headless Tickman",
    "Kizu Kenji",
    "Plague Doctor Crow",
    "Spirit Frank",
    "Vecna",
    "Wasabi In The Eyes"
  ],
  "Dodgebrawl": [
    "Dodge Or Die",
    "Hug Or Hurl",
    "Moonbark Meadow",
    "Rebound Ring",
    "Side Hustle",
    "Squish Court",
    "Wispwillow Ward"
  ],
  "Subway Run": [
    "Backtrack Attack",
    "Choo Choo Showdown",
    "Loopy Line",
    "Metro Mayhem",
    "T-Rail Rush",
    "Toot Town",
    "Trainbow Road"
  ],
  "Knockout 5v5": [
    "Brawlerverse"
  ],
  "Trio Wipeout": [
    "Nippy Narrows",
    "Overpower Outpost",
    "Permafrost Bayou",
    "Slay Bay"
  ],
  "Trio Gem Grab": [
    "Cold Cash",
    "Mine All Mine",
    "Polar Payoff",
    "Treasure Pressure"
  ],
  "Upside Showdown": [
    "Kroket"
  ],
  "Love Bombing": [
    "Caged Hearts",
    "Crush & Burn",
    "Lovers Lane"
  ],
  "Duo Mega Boss": [
    "Mega Bear Shade",
    "Mega Brawlentines Angelo",
    "Mega Heartbroken Rico",
    "Mega Love Potion Squeak"
  ],
  "Safe Blast": [
    "Fast Blast Alley",
    "Fuseyard",
    "Gunpowder Gangway",
    "Safe Bet",
    "Violent Withdrawal"
  ],
  "Shadow Smash": [
    "Copycat Carnival",
    "Doppelzone",
    "Imposter Pathway",
    "Moonveil Mansion",
    "Silver Shadow Circus",
    "The Big Top",
    "Web Of Shadows"
  ],
  "Super Ball": [
    "Backnet Bonanza",
    "Fox In The Box",
    "Goalmouth Scramble",
    "Impossible Arena",
    "Midfield Madness",
    "Penalty Park"
  ],
  "5 Player Void Boss": [
    "Void Colette",
    "Void Master Finx"
  ]
}